mindset/__init__.py
mindset/__version__.py
mindset/api_requests.py
mindset/utils/__init__.py
mindset/utils/date_utils.py
mindset/utils/request_base.py
mindset/utils/tools.py
lins_mindsetrequests-2.2.2.dist-info/LICENSE
lins_mindsetrequests-2.2.2.dist-info/METADATA
lins_mindsetrequests-2.2.2.dist-info/WHEEL
lins_mindsetrequests-2.2.2.dist-info/top_level.txt
lins_mindsetrequests-2.2.2.dist-info/RECORD
