Metadata-Version: 2.1
Name: lins-mindsetrequests
Version: 2.2.2
Summary: Lib para consumo da api mindset do Grupo Lins Ferrão.
Home-page: https://bitbucket.org/grupolinsferrao/pypck-lins-mindset-requests
Author: Diego Magalhães
Author-email: diego.magalhaes@dbccompany.com.br
License: UNKNOWN
Platform: UNKNOWN
Classifier: Programming Language :: Python :: 3
Classifier: License :: OSI Approved :: MIT License
Classifier: Operating System :: OS Independent
Requires-Python: >=3.6
Requires-Dist: requests
Requires-Dist: pytz
